{
  "Á": "A",
  "À": "A",
  "Â": "A",
  "Ä": "A",
  "Ǎ": "A",
  "Ă": "A",
  "Ā": "A",
  "Ã": "A",
  "Å": "A",
  "Ą": "A",
  "á": "a",
  "à": "a",
  "â": "a",
  "ä": "a",
  "ǎ": "a",
  "ă": "a",
  "ā": "a",
  "ã": "a",
  "å": "a",
  "ą": "a",
  "ắ": "a",
  "ằ": "a",
  "ẳ": "a",
  "ẵ": "a",
  "ặ": "a",
  "ầ": "a",
  "ẩ": "a",
  "ẫ": "a",
  "ấ": "a",
  "ậ": "a",
  "Æ": "Ae",
  "Ǣ": "Ae",
  "Ǽ": "Ae",
  "æ": "ae",
  "ǣ": "ae",
  "ǽ": "ae",
  "Α": "Alpha",
  "α": "alpha",
  "Β": "Beta",
  "β": "beta",
  "Ć": "C",
  "Ċ": "C",
  "Ĉ": "C",
  "Č": "C",
  "Ç": "C",
  "ć": "c",
  "ċ": "c",
  "ĉ": "c",
  "č": "c",
  "ç": "c",
  "Χ": "Chi",
  "χ": "chi",
  "Ď": "D",
  "Đ": "D",
  "Ḍ": "D",
  "Ð": "D",
  "Ḑ": "D",
  "ď": "d",
  "đ": "d",
  "ḍ": "d",
  "ð": "d",
  "ḑ": "d",
  "Δ": "Delta",
  "δ": "delta",
  "É": "E",
  "È": "E",
  "Ė": "E",
  "Ê": "E",
  "Ë": "E",
  "Ě": "E",
  "Ĕ": "E",
  "Ē": "E",
  "Ẽ": "E",
  "Ę": "E",
  "Ẹ": "E",
  "Ɛ": "E",
  "Ǝ": "E",
  "Ə": "E",
  "Ề": "E",
  "Ể": "E",
  "Ễ": "E",
  "Ế": "E",
  "Ệ": "E",
  "é": "e",
  "è": "e",
  "ė": "e",
  "ê": "e",
  "ë": "e",
  "ě": "e",
  "ĕ": "e",
  "ē": "e",
  "ẽ": "e",
  "ę": "e",
  "ẹ": "e",
  "ɛ": "e",
  "ǝ": "e",
  "ə": "e",
  "ề": "e",
  "ể": "e",
  "ễ": "e",
  "ế": "e",
  "ệ": "e",
  "Ε": "Epsilon",
  "ε": "Epsilon",
  "Η": "Eta",
  "η": "eta",
  "Ġ": "G",
  "Ĝ": "G",
  "Ğ": "G",
  "Ģ": "G",
  "ġ": "g",
  "ĝ": "g",
  "ğ": "g",
  "ģ": "g",
  "Γ": "Gamma",
  "γ": "gamma",
  "Ĥ": "H",
  "Ħ": "H",
  "Ḥ": "H",
  "ĥ": "h",
  "ħ": "h",
  "ḥ": "h",
  "ḩ": "h",
  "İ": "I",
  "Í": "I",
  "Ì": "I",
  "Î": "I",
  "Ï": "I",
  "Ǐ": "I",
  "Ĭ": "I",
  "Ī": "I",
  "Ĩ": "I",
  "Į": "I",
  "Ị": "I",
  "ı": "i",
  "í": "i",
  "ì": "i",
  "î": "i",
  "ï": "i",
  "ǐ": "i",
  "ĭ": "i",
  "ī": "i",
  "ĩ": "i",
  "į": "i",
  "ị": "i",
  "Ι": "Iota",
  "ι": "iota",
  "Ĵ": "J",
  "ĵ": "j",
  "Ķ": "K",
  "ķ": "k",
  "Κ": "Kappa",
  "κ": "kappa",
  "Ĺ": "L",
  "Ŀ": "L",
  "Ľ": "L",
  "Ļ": "L",
  "Ł": "L",
  "Ḷ": "L",
  "Ḹ": "L",
  "ĺ": "l",
  "ŀ": "l",
  "ľ": "l",
  "ļ": "l",
  "ł": "l",
  "ḷ": "l",
  "ḹ": "l",
  "Λ": "Lamda",
  "λ": "lamda",
  "Ṃ": "M",
  "ṃ": "m",
  "Μ": "Mu",
  "μ": "mu",
  "Ń": "N",
  "Ň": "N",
  "Ñ": "N",
  "Ņ": "N",
  "Ṇ": "N",
  "Ŋ": "N",
  "ń": "n",
  "ň": "n",
  "ñ": "n",
  "ņ": "n",
  "ṇ": "n",
  "ŋ": "n",
  "Ν": "Nu",
  "ν": "nu",
  "Ó": "O",
  "Ò": "O",
  "Ô": "O",
  "Ö": "O",
  "Ǒ": "O",
  "Ŏ": "O",
  "Ō": "O",
  "Õ": "O",
  "Ǫ": "O",
  "Ọ": "O",
  "Ő": "O",
  "Ø": "O",
  "Ɔ": "O",
  "ó": "o",
  "ò": "o",
  "ô": "o",
  "ö": "o",
  "ǒ": "o",
  "ŏ": "o",
  "ō": "o",
  "õ": "o",
  "ǫ": "o",
  "ọ": "o",
  "ő": "o",
  "ø": "o",
  "ɔ": "o",
  "ơ": "o",
  "ồ": "o",
  "Œ": "Oe",
  "œ": "oe",
  "Ω": "Omega",
  "ω": "omega",
  "Ο": "Omicron",
  "ο": "omicron",
  "Φ": "Phi",
  "φ": "phi",
  "Π": "Pi",
  "π": "pi",
  "Ψ": "Psi",
  "ψ": "psi",
  "Ŕ": "R",
  "Ř": "R",
  "Ŗ": "R",
  "Ṛ": "R",
  "Ṝ": "R",
  "ŕ": "r",
  "ř": "r",
  "ŗ": "r",
  "ṛ": "r",
  "ṝ": "r",
  "Ρ": "Rho",
  "ρ": "rho",
  "Ś": "S",
  "Ŝ": "S",
  "Š": "S",
  "Ş": "S",
  "Ș": "S",
  "Ṣ": "S",
  "ś": "s",
  "ŝ": "s",
  "š": "s",
  "ş": "s",
  "ș": "s",
  "ṣ": "s",
  "ß": "ss",
  "Σ": "Sigma",
  "σ": "sigma",
  "ς": "sigma",
  "Ť": "T",
  "Ţ": "T",
  "Ț": "T",
  "Ṭ": "T",
  "ť": "t",
  "ţ": "t",
  "ț": "t",
  "ṭ": "t",
  "Þ": "Th",
  "þ": "th",
  "Θ": "Theta",
  "θ": "theta",
  "Τ": "Tau",
  "τ": "tau",
  "Ú": "U",
  "Ù": "U",
  "Û": "U",
  "Ü": "U",
  "Ǔ": "U",
  "Ŭ": "U",
  "Ū": "U",
  "Ũ": "U",
  "Ů": "U",
  "Ų": "U",
  "Ụ": "U",
  "Ű": "U",
  "Ǘ": "U",
  "Ǜ": "U",
  "Ǚ": "U",
  "Ǖ": "U",
  "Υ": "Upsilon",
  "υ": "upsilon",
  "ú": "u",
  "ù": "u",
  "û": "u",
  "ü": "u",
  "ǔ": "u",
  "ŭ": "u",
  "ū": "u",
  "ũ": "u",
  "ů": "u",
  "ų": "u",
  "ụ": "u",
  "ű": "u",
  "ǘ": "u",
  "ǜ": "u",
  "ǚ": "u",
  "ǖ": "u",
  "Ŵ": "W",
  "ŵ": "w",
  "Ξ": "Xi",
  "ξ": "xi",
  "Ý": "Y",
  "Ŷ": "Y",
  "Ÿ": "Y",
  "Ỹ": "Y",
  "Ȳ": "Y",
  "ý": "y",
  "ŷ": "y",
  "ÿ": "y",
  "ỹ": "y",
  "ȳ": "y",
  "Ź": "Z",
  "Ż": "Z",
  "Ž": "Z",
  "ź": "z",
  "ż": "z",
  "ž": "z",
  "Ζ": "Zeta",
  "ζ": "zeta"
}